source-transform.pth
source_transform/__init__.py
source_transform/discovery.py
source_transform/meta_path.py
source_transform/transform.py
source_transform-0.1.2.dist-info/LICENSE
source_transform-0.1.2.dist-info/METADATA
source_transform-0.1.2.dist-info/WHEEL
source_transform-0.1.2.dist-info/top_level.txt
source_transform-0.1.2.dist-info/RECORD
