Metadata-Version: 2.1
Name: source-transform
Version: 0.1.2
Summary: Python source transformation framework
Home-page: https://github.com/bakkerthehacker/source-transform/
Author: Grant Bakker
Author-email: grant@bakker.pw
License: UNKNOWN
Platform: UNKNOWN
Classifier: Programming Language :: Python :: 2.7
Classifier: Programming Language :: Python :: 3
Classifier: Operating System :: OS Independent
Classifier: License :: OSI Approved :: MIT License
Requires-Dist: six
Requires-Dist: toolz
